sonarlight/__init__.py
sonarlight/sonar.py
sonarlight/sonar_class.py
sonarlight/version.py
sonarlight-0.1.7.dist-info/LICENSE
sonarlight-0.1.7.dist-info/METADATA
sonarlight-0.1.7.dist-info/WHEEL
sonarlight-0.1.7.dist-info/top_level.txt
sonarlight-0.1.7.dist-info/RECORD
